<annotation>
	<folder></folder>
	<filename>1802_jpg.rf.6d80ddf34005175c964b22a2fcad6847.jpg</filename>
	<path>1802_jpg.rf.6d80ddf34005175c964b22a2fcad6847.jpg</path>
	<source>
		<database>roboflow.ai</database>
	</source>
	<size>
		<width>412</width>
		<height>412</height>
		<depth>3</depth>
	</size>
	<segmented>0</segmented>
	<object>
		<name>insulator</name>
		<pose>Unspecified</pose>
		<truncated>0</truncated>
		<difficult>0</difficult>
		<occluded>0</occluded>
		<bndbox>
			<xmin>43</xmin>
			<xmax>336</xmax>
			<ymin>172</ymin>
			<ymax>241</ymax>
		</bndbox>
	</object>
</annotation>
